impose/__init__.py
impose/__main__.py
impose/_version.py
impose/_version_save.py
impose/data.py
impose/flblend.py
impose/session.py
impose/util.py
impose/formats/__init__.py
impose/formats/fmt_bf_generic.py
impose/formats/fmt_bm_bmlab.py
impose/formats/fmt_fl_ometif.py
impose/formats/fmt_fl_zeiss.py
impose/geometry/__init__.py
impose/geometry/mask.py
impose/geometry/shapes/__init__.py
impose/geometry/shapes/base.py
impose/geometry/shapes/sh_circle.py
impose/geometry/shapes/sh_ellipse.py
impose/geometry/shapes/sh_polygon.py
impose/geometry/shapes/sh_rectangle.py
impose/gui/__init__.py
impose/gui/collect.py
impose/gui/collect.ui
impose/gui/collect_pgrois.py
impose/gui/collect_shape_controls.py
impose/gui/collect_shape_controls.ui
impose/gui/colocalize.py
impose/gui/colocalize.ui
impose/gui/colocalize_pgrois.py
impose/gui/dlg_edit_circle.ui
impose/gui/dlg_edit_ellipse.ui
impose/gui/dlg_edit_polygon.ui
impose/gui/dlg_edit_rectangle.ui
impose/gui/dlg_edit_shape.py
impose/gui/main.py
impose/gui/main.ui
impose/gui/visualize.py
impose/gui/visualize.ui
impose/gui/widgets/__init__.py
impose/gui/widgets/simple_image_view.py
impose/gui/widgets/simple_plot_widget.py
impose/gui/widgets/wait_cursor.py
impose/structure/__init__.py
impose/structure/composite.py
impose/structure/composite_stack.py
impose/structure/layer.py
impose-0.4.10.dist-info/LICENSE
impose-0.4.10.dist-info/METADATA
impose-0.4.10.dist-info/WHEEL
impose-0.4.10.dist-info/top_level.txt
impose-0.4.10.dist-info/RECORD
