Metadata-Version: 2.1
Name: impose
Version: 0.4.10
Summary: Fit and superimpose shapes from different imaging modalities
Home-page: https://github.com/GuckLab/impose
Maintainer: Paul Müller
Maintainer-email: dev@craban.de
License: GPL v3
Keywords: image analysis,biology,microscopy
Platform: ALL
Classifier: Operating System :: OS Independent
Classifier: Programming Language :: Python :: 3
Classifier: Topic :: Scientific/Engineering :: Visualization
Classifier: Intended Audience :: Science/Research
Requires-Python: >=3.9
License-File: LICENSE
Requires-Dist: czifile ==2019.7.2
Requires-Dist: bmlab ==0.6.1
Requires-Dist: h5py >=3.11.0
Requires-Dist: imageio
Requires-Dist: numpy >=1.17.0
Requires-Dist: pyqt6 >=6.2.0
Requires-Dist: pyqtgraph ==0.13.7
Requires-Dist: scikit-image >=0.17.2
Requires-Dist: scipy >=0.12.0
Requires-Dist: tifffile ==2024.5.10
